setup.py
performance_control/ArgData.py
performance_control/ComplexityCalc.py
performance_control/Logger.py
performance_control/PerformanceControllerException.py
performance_control/Timeout.py
performance_control/__init__.py
performance_control.egg-info/PKG-INFO
performance_control.egg-info/SOURCES.txt
performance_control.egg-info/dependency_links.txt
performance_control.egg-info/not-zip-safe
performance_control.egg-info/requires.txt
performance_control.egg-info/top_level.txt