Metadata-Version: 1.0
Name: performance-control
Version: 0.2
Summary: This is a package to calculate time complexity of algorithm
Home-page: https://github.com/AGHPythonCourse2017/zad2-kanes115.git
Author: Dominik Stanaszek
Author-email: dominikstanaszek@icloud.com
License: NONE
Platform: UNKNOWN
